petram/__init__.py
petram/geom/__init__.py
petram/geom/geom_id.py
petram/geom/geom_info_palette.py
petram/geom/geom_model.py
petram/geom/geom_primitives.py
petram/geom/geom_sel_buttons.py
petram/geom/geom_sequence_operator.py
petram/geom/geom_utils.py
petram/geom/gmsh_config.py
petram/geom/gmsh_geom_model.py
petram/geom/gmsh_geom_wrapper.py
petram/geom/gmsh_primitives.py
petram/geom/occ_cbook.py
petram/geom/occ_geom_model.py
petram/geom/occ_geom_wrapper.py
petram/geom/occ_heal_extra.py
petram/geom/occ_heal_shape.py
petram/geom/occ_inspect.py
petram/geom/read_brep_occ.py
petram/geom/read_gmsh.py
petram/geom/vtable_geom.py
petram/mesh/__init__.py
petram/mesh/gmsh2mfem.py
petram/mesh/gmsh_helper.py
petram/mesh/gmsh_mesh_actions.py
petram/mesh/gmsh_mesh_model.py
petram/mesh/gmsh_mesh_wrapper.py
petram/mesh/mesh_sequence_operator.py
PetraM_Geom-1.4.6.dist-info/LICENSE
PetraM_Geom-1.4.6.dist-info/METADATA
PetraM_Geom-1.4.6.dist-info/WHEEL
PetraM_Geom-1.4.6.dist-info/top_level.txt
PetraM_Geom-1.4.6.dist-info/RECORD
